setup.py
Dogeon.egg-info/PKG-INFO
Dogeon.egg-info/SOURCES.txt
Dogeon.egg-info/dependency_links.txt
Dogeon.egg-info/top_level.txt
dson/__init__.py
dson/_compact.py
dson/decoder.py
dson/encoder.py
dson/scanner.py