Metadata-Version: 1.1
Name: Dogeon
Version: 1.0.1
Summary: Simple, fast, extensible DSON encoder/decoder for Python
Home-page: https://github.com/soasme/dogeon
Author: Ju Lin
Author-email: soasme@gmail.com
License: MIT License
Keywords: DSON dson Dogeon
Platform: UNKNOWN
Classifier: Development Status :: 4 - Beta
Classifier: Intended Audience :: Developers
Classifier: Operating System :: OS Independent
Classifier: Programming Language :: Python
Classifier: Programming Language :: Python :: 3
Classifier: License :: OSI Approved :: MIT License
Classifier: Topic :: Internet :: WWW/HTTP :: Dynamic Content
Classifier: Topic :: Software Development :: Libraries :: Python Modules
